{
  "summaryVersion": 1,
  "sourceCaptureId": "session-20260429-183031-673",
  "startedAtUtc": "2026-04-29T18:30:31.6734675\u002B00:00",
  "finishedAtUtc": "2026-04-29T18:37:34.4871973\u002B00:00",
  "combo": {
    "carKey": "car-156-mercedesamgevogt3",
    "trackKey": "track-252-nurburgring-combined",
    "sessionKey": "race"
  },
  "car": {
    "carId": 156,
    "carPath": "mercedesamgevogt3",
    "carScreenName": "Mercedes-AMG GT3 2020",
    "carScreenNameShort": "Mercedes GT3 2020",
    "carClassId": 4098,
    "carClassShortName": null,
    "carClassEstLapTimeSeconds": 480.8602,
    "driverCarFuelMaxLiters": 106,
    "driverCarFuelKgPerLiter": 0.75,
    "driverCarEstLapTimeSeconds": 480.8602,
    "driverCarVersion": "2026.04.15.02",
    "driverGearboxType": "Sequential",
    "driverSetupName": "nurburgring combined\\26s2\\GO 26S2 Nords24hrs AMGGT3 Safe R .sto",
    "driverSetupIsModified": true
  },
  "track": {
    "trackId": 252,
    "trackName": "nurburgring combined",
    "trackDisplayName": "Gesamtstrecke 24h",
    "trackConfigName": null,
    "trackLengthKm": 25.1764,
    "trackCity": "N\u00FCrburg",
    "trackCountry": "Germany",
    "trackNumTurns": 170,
    "trackType": "road course",
    "trackVersion": "2026.03.30.02"
  },
  "session": {
    "currentSessionNum": 0,
    "sessionNum": 0,
    "sessionType": "Race",
    "sessionName": "RACE",
    "sessionTime": "7200.0000 sec",
    "sessionLaps": "unlimited",
    "eventType": "Race",
    "category": "SportsCar",
    "official": false,
    "teamRacing": false,
    "seriesId": 0,
    "seasonId": 0,
    "sessionId": 0,
    "subSessionId": 0,
    "buildVersion": "2026.04.21.01"
  },
  "conditions": {
    "airTempC": 20.398788452148438,
    "trackTempCrewC": 32.77777099609375,
    "trackWetness": 1,
    "weatherDeclaredWet": false,
    "playerTireCompound": 0,
    "trackWeatherType": "Realistic",
    "trackSkies": "Dynamic",
    "trackPrecipitationPercent": 0,
    "sessionTrackRubberState": "moderate usage"
  },
  "metrics": {
    "sampleFrameCount": 25366,
    "droppedFrameCount": 0,
    "sessionInfoSnapshotCount": 5,
    "captureDurationSeconds": 422.7971031,
    "onTrackTimeSeconds": 3.133333333335827,
    "pitRoadTimeSeconds": 421.19999999979063,
    "movingTimeSeconds": 0,
    "validGreenTimeSeconds": 0,
    "validDistanceLaps": 0,
    "completedValidLaps": 0,
    "fuelUsedLiters": 0,
    "fuelAddedLiters": 0,
    "fuelPerHourLiters": null,
    "fuelPerLapLiters": null,
    "averageLapSeconds": null,
    "medianLapSeconds": null,
    "bestLapSeconds": null,
    "startingFuelLiters": 104.94000244140625,
    "endingFuelLiters": 104.94000244140625,
    "minimumFuelLiters": 104.94000244140625,
    "maximumFuelLiters": 104.94000244140625,
    "pitRoadEntryCount": 1,
    "pitServiceCount": 0,
    "stintCount": 0,
    "averageStintLaps": null,
    "averageStintSeconds": null,
    "averageStintFuelPerLapLiters": null,
    "averagePitLaneSeconds": 421.19999999979063,
    "averagePitStallSeconds": 421.19999999979063,
    "averagePitServiceSeconds": null,
    "observedFuelFillRateLitersPerSecond": null,
    "averageTireChangePitServiceSeconds": null,
    "averageNoTirePitServiceSeconds": 421.19999999979063
  },
  "stints": [],
  "pitStops": [
    {
      "stopNumber": 1,
      "entryRaceTimeSeconds": 154.23333536785788,
      "exitRaceTimeSeconds": 575.4333353676485,
      "pitLaneSeconds": 421.19999999979063,
      "entryLapCompleted": -1,
      "exitLapCompleted": 0,
      "pitStallSeconds": 421.19999999979063,
      "serviceActiveSeconds": null,
      "fuelBeforeLiters": 104.94000244140625,
      "fuelAfterLiters": 104.94000244140625,
      "fuelAddedLiters": 0,
      "fuelFillRateLitersPerSecond": null,
      "tireSetChanged": false,
      "fastRepairUsed": false,
      "pitServiceFlags": 63,
      "confidenceFlags": [
        "team_car_array",
        "local_fuel_scalar",
        "pit_stall_signal"
      ]
    }
  ],
  "quality": {
    "confidence": "none",
    "contributesToBaseline": false,
    "reasons": [
      "short_green_sample",
      "insufficient_distance",
      "no_completed_laps",
      "no_reliable_fuel_per_lap"
    ]
  },
  "appVersion": {
    "productName": "TmrOverlay.App",
    "version": "1.0.0.0",
    "informationalVersion": "1.0.0\u002B4ba089e1444428e90c01fc8e8e3265c6b52bd86e",
    "runtimeVersion": ".NET 8.0.26",
    "operatingSystem": "Microsoft Windows 10.0.26200",
    "processArchitecture": "X64"
  },
  "collectionModelVersion": 1
}